{
  "id": "engineering_upgrade_I",
  "name": "Engineering Upgrade I",
  "description": "Permanently increases engineering XP gain by 10%, speed by 5%, success rate by 5%, and yield by 5%",
  "type": "permanent",
  "scope": "skill",
  "skillId": "engineering",
  "tier": "I",
  "price": 1500,
  "bonuses": {
    "experienceMultiplier": 1.1,
    "speedMultiplier": 0.95,
    "successRateBonus": 0.05,
    "yieldMultiplier": 1.05
  },
  "requirements": {},
  "nameKey": "upgrade.engineering_upgrade_I.name",
  "descriptionKey": "upgrade.engineering_upgrade_I.description"
}
