{
  "id": "ambush",
  "name": "Ambush",
  "description": "Strike from stealth, dealing massive damage. Only usable while stealthed.",
  "type": "active",
  "maxLevel": 5,
  "requirements": {
    "class": [
      "rogue"
    ]
  },
  "unlockLevel": 6,
  "prerequisites": [
    "stealth"
  ],
  "manaCost": 25,
  "cooldown": 0,
  "target": "enemy",
  "effect": {
    "damage": {
      "base": 80,
      "scaling": {
        "stat": "dexterity",
        "multiplier": 2.5
      }
    }
  },
  "nameKey": "skill.ambush.name",
  "descriptionKey": "skill.ambush.description"
}
